LICENSE
README.md
setup.py
CVE_2012_5321.egg-info/PKG-INFO
CVE_2012_5321.egg-info/SOURCES.txt
CVE_2012_5321.egg-info/dependency_links.txt
CVE_2012_5321.egg-info/entry_points.txt
CVE_2012_5321.egg-info/requires.txt
CVE_2012_5321.egg-info/top_level.txt
cve20125321/main.py
cve20125321/includes/__init__.py
cve20125321/includes/bot.py
cve20125321/includes/filereader.py
cve20125321/includes/scan.py
cve20125321/includes/writefile.py
cve20125321/utils/__init__.py
cve20125321/utils/configure.py
cve20125321/utils/const.py
cve20125321/utils/helpers.py
cve20125321/utils/status.py